{"cameraMode":{"drawMode":0,"name":"Shaded","section":"Shading Mode"},"sceneLighting":false,"audioPlay":false,"sceneViewState":{"m_AlwaysRefresh":false,"showFog":true,"showSkybox":true,"showFlares":true,"showImageEffects":true,"showParticleSystems":true,"showVisualEffectGraphs":true,"m_FxEnabled":true},"in2DMode":false,"pivot":{"x":926.552978515625,"y":396.7841796875,"z":128.346435546875},"rotation":{"x":0.16059589385986329,"y":-0.6793580651283264,"z":0.15613088011741639,"w":0.6987887620925903},"size":-3.0339744091033937,"orthographic":false}